[{"artist":"Mantequilla","name":"Lq","url":"https://tabs.ultimate-guitar.com/tab/mantequilla/lq_chords_379660","rating":0,"numberRates":0,"type":"Chords","difficulty":"advanced","chords":["C","G","F","C","G","F","G","C","G","F","G","C","G","F","G","C","G","F","G","Am","G","F","Am","G","F","C","G","F","G","C","G","F","G","C","G","F","G","C","G","F","G","C","G","F","G","C","G","F","G","Am","G","F","Am","G","F","C","G","F","G","C","G","F","G"]},{"artist":"B.o.B","name":"Lq","url":"https://tabs.ultimate-guitar.com/tab/b_o_b/lq_chords_1731382","rating":0,"numberRates":0,"type":"Chords","difficulty":"novice","chords":["Bm","A","G","Bm","A","G","Bm","A","G","Bm","A","G","Bm","A","G","Em","D/F#","G","Bm","A","G","Bm","A","G","Bm","A","G","Em","D/F#","G","Bm","A","G","Bm","A","G","Bm","A","G","Em","D/F#","G","Bm","A","G","Bm","A","G","Bm","A","G","Bm","A","G","Em","D/F#","G","Em","D/F#","G","Bm","A","G","Bm","A","G","Bm","A","G","Em","D/F#","G","Em","D/F#","G","Em","D/F#","G"]}]